{"0":{"id":"male0","group":0,"rank":1},"1":{"id":"male1","group":1,"rank":2},"2":{"id":"male2","group":0,"rank":3},"3":{"id":"male3","group":2,"rank":4},"4":{"id":"male4","group":3,"rank":5},"5":{"id":"female0","group":0,"rank":10},"6":{"id":"female1","group":0,"rank":11},"7":{"id":"female2","group":0,"rank":6},"8":{"id":"female3","group":0,"rank":12},"9":{"id":" female4","group":0,"rank":9},"10":{"id":" female5","group":0,"rank":7},"11":{"id":" female6","group":0,"rank":8},"12":{"id":" female7","group":1,"rank":18},"13":{"id":" female8","group":1,"rank":19},"14":{"id":" female9","group":1,"rank":20},"15":{"id":" female10","group":0,"rank":13},"16":{"id":" female11","group":0,"rank":14},"17":{"id":" female12","group":0,"rank":15},"18":{"id":" female13","group":0,"rank":16},"19":{"id":" female14","group":0,"rank":17}}